gwf_utils/Gwf.py
gwf_utils/_version.py
gwf_utils/gwf_functions.py
gwf_utils/cli/gwf_subset.py
gwf_utils-0.1.2.dist-info/METADATA
gwf_utils-0.1.2.dist-info/WHEEL
gwf_utils-0.1.2.dist-info/entry_points.txt
gwf_utils-0.1.2.dist-info/top_level.txt
gwf_utils-0.1.2.dist-info/RECORD
